s2v/__init__.py
s2v/client/__init__.py
s2v/client/auth.py
s2v/client/cli.py
s2v/client/lib.py
s2v/client/py.typed
s2v/client/viz/__init__.py
s2v/client/viz/assets/favicon.ico
s2v/client/viz/assets/logo.png
s2v/client/viz/assets/styles.css
s2v/client/viz/assets/tooltip.css
s2v/client/viz/entity_styles.py
s2v/client/viz/jaal.py
s2v/client/viz/layout.py
s2v/client/viz/parse_dataframe.py
s2v/client/viz/yaml_model_parser.py
s2v/version.py
s2v_client-1.2.15.dist-info/WHEEL
s2v_client-1.2.15.dist-info/METADATA
s2v_client-1.2.15.dist-info/entry_points.txt
s2v_client-1.2.15.dist-info/RECORD
