Metadata-Version: 2.1
Name: s2v-client
Author: Reeeliance IM GmbH
Summary: Stream2Vault Client
Classifier: Development Status :: 3 - Alpha
Classifier: Environment :: Console
Classifier: Programming Language :: Python :: 3
Requires-Python: >=3.12
Requires-Dist: click~=8.1.8
Requires-Dist: dash~=2.18.2
Requires-Dist: dash-bootstrap-components~=1.7.1
Requires-Dist: google-auth~=2.38.0
Requires-Dist: httpx~=0.28.1
Requires-Dist: msal~=1.31.1
Requires-Dist: platformdirs~=4.3.6
Requires-Dist: pyyaml~=6.0.2
Requires-Dist: visdcc~=0.0.50
Requires-Dist: yaspin~=3.1.0
Version: 1.2.15
